MANIFEST.in
README.md
requirements.txt
setup.cfg
setup.py
napalm_dlink/__init__.py
napalm_dlink/dlink.py
napalm_dlink.egg-info/PKG-INFO
napalm_dlink.egg-info/SOURCES.txt
napalm_dlink.egg-info/dependency_links.txt
napalm_dlink.egg-info/requires.txt
napalm_dlink.egg-info/top_level.txt
napalm_dlink/utils/__init__.py
napalm_dlink/utils/textfsm_templates/get_interfaces_counters.tpl
napalm_dlink/utils/textfsm_templates/get_interfaces_errors.tpl
napalm_dlink/utils/textfsm_templates/get_ntp_servers.tpl
napalm_dlink/utils/textfsm_templates/show_arpentry.tpl
napalm_dlink/utils/textfsm_templates/show_fdb.tpl
napalm_dlink/utils/textfsm_templates/show_lldp_remote_ports_detail.tpl
napalm_dlink/utils/textfsm_templates/show_ports.tpl
napalm_dlink/utils/textfsm_templates/show_ports_ip.tpl
napalm_dlink/utils/textfsm_templates/show_switch.tpl
napalm_dlink/utils/textfsm_templates/snmp.tpl
napalm_dlink/utils/textfsm_templates/snmp_community.tpl
napalm_dlink/utils/textfsm_templates/users.tpl