Metadata-Version: 2.1
Name: napalm-dlink
Version: 0.1.0
Summary: NAPALM driver for Dlink
Home-page: https://github.com/napalm-automation/napalm-dlink
Author: Nikolay Chobanov
Author-email: hromus@gmail.com
License: UNKNOWN
Platform: UNKNOWN
Classifier: Topic :: Utilities
Classifier: Programming Language :: Python
Classifier: Programming Language :: Python :: 3
Classifier: Programming Language :: Python :: 3.7
Classifier: Operating System :: POSIX :: Linux
